{"todoItems":[{"id":1,"task":"homework"},{"id":2,"task":"groceries"},{"id":3},{"id":4,"task":"learn node.js"},{"id":5},{"id":6},{"id":7,"task":"find out why show func is creating an empty task"},{"id":8,"task":"remove show function and test your add function again"},{"id":9,"task":"do the laundry"},{"id":10},{"id":11},{"id":12,"task":"check command type"},{"id":13,"task":"make the mark as done further"},{"id":14,"done":"[X]","task":"check done function"},{"id":15,"done":"[X]","task":"love meow"},{"id":16,"done":"[ ]","task":"14"},{"id":17,"done":"[X]","task":"check if modules are working"}]}
